ggtool/__init__.py
ggtool/main.py
ggtool/util/__init__.py
ggtool/util/password.py
ggtool-0.0.1.dist-info/METADATA
ggtool-0.0.1.dist-info/WHEEL
ggtool-0.0.1.dist-info/entry_points.txt
ggtool-0.0.1.dist-info/top_level.txt
ggtool-0.0.1.dist-info/zip-safe
ggtool-0.0.1.dist-info/RECORD
